math_rounding/__init__.py
math_rounding/rounding.py
math_rounding/version.py
math_rounding-1.0.1.dist-info/METADATA
math_rounding-1.0.1.dist-info/WHEEL
math_rounding-1.0.1.dist-info/licenses/LICENSE
math_rounding-1.0.1.dist-info/RECORD
