Metadata-Version: 2.3
Name: math-rounding
Version: 1.0.1
Summary: The package contains mathematical rounding function
Project-URL: Homepage, https://github.com/alexstaf/math-rounding
Project-URL: Issues, https://github.com/alexstaf/math-rounding/issues
Project-URL: Changelog, https://github.com/alexstaf/math-rounding/blob/main/CHANGELOG.md
Author: alexstaf
Classifier: License :: OSI Approved :: MIT License
Classifier: Operating System :: OS Independent
Classifier: Programming Language :: Python :: 3
Requires-Python: >=3.8
Requires-Dist: dummy-decorator~=1.0
Provides-Extra: numba
Requires-Dist: numba~=0.58; extra == 'numba'
